{
  "id": "lvgl-st7789-status-settings-ui",
  "name": "lvgl-st7789-status-settings-ui",
  "title": "LVGL ST7789 状态屏设置系统",
  "description": "",
  "status": "completed",
  "dev_type": null,
  "scope": null,
  "package": null,
  "priority": "P2",
  "creator": "Ming",
  "assignee": "Ming",
  "createdAt": "2026-05-26",
  "completedAt": "2026-05-26",
  "branch": null,
  "base_branch": "main",
  "worktree_path": null,
  "commit": null,
  "pr_url": null,
  "subtasks": [],
  "children": [],
  "parent": null,
  "relatedFiles": [],
  "notes": "",
  "meta": {}
}